django_db_migrator/__init__.py
django_db_migrator/cli.py
django_db_migrator/migrator.py
django_db_migrator-0.1.1.dist-info/METADATA
django_db_migrator-0.1.1.dist-info/WHEEL
django_db_migrator-0.1.1.dist-info/entry_points.txt
django_db_migrator-0.1.1.dist-info/top_level.txt
django_db_migrator-0.1.1.dist-info/RECORD
