Metadata-Version: 2.4
Name: django-db-migrator
Version: 0.1.1
Summary: Easily migrate your Django PostgreSQL database between platforms
Home-page: https://github.com/yourusername/django-db-migrator
Author: Your Name
Classifier: Programming Language :: Python :: 3
Classifier: License :: OSI Approved :: MIT License
Requires-Dist: python-dotenv
